{
  "advantage_mean": {
    "steps": [
      200
    ],
    "timestamps": [
      "2026-03-18T21:33:44.480682"
    ],
    "values": [
      -0.05868198871612549
    ]
  },
  "agent_grad_norm": {
    "steps": [
      200
    ],
    "timestamps": [
      "2026-03-18T21:33:44.480692"
    ],
    "values": [
      0.05810725316405296
    ]
  },
  "critic_grad_norm": {
    "steps": [
      200
    ],
    "timestamps": [
      "2026-03-18T21:33:44.480656"
    ],
    "values": [
      0.8470007181167603
    ]
  },
  "critic_loss": {
    "steps": [
      200
    ],
    "timestamps": [
      "2026-03-18T21:33:44.480642"
    ],
    "values": [
      0.005122343078255653
    ]
  },
  "ep_length_mean": {
    "steps": [
      200
    ],
    "timestamps": [
      "2026-03-18T21:33:44.419877"
    ],
    "values": [
      20.0
    ]
  },
  "pg_loss": {
    "steps": [
      200
    ],
    "timestamps": [
      "2026-03-18T21:33:44.480685"
    ],
    "values": [
      0.05683436244726181
    ]
  },
  "pi_max": {
    "steps": [
      200
    ],
    "timestamps": [
      "2026-03-18T21:33:44.480734"
    ],
    "values": [
      0.2334897041320801
    ]
  },
  "q_taken_mean": {
    "steps": [
      200
    ],
    "timestamps": [
      "2026-03-18T21:33:44.480662"
    ],
    "values": [
      0.23561962127685546
    ]
  },
  "return_mean": {
    "steps": [
      200
    ],
    "timestamps": [
      "2026-03-18T21:33:44.419790"
    ],
    "values": [
      0.0
    ]
  },
  "return_std": {
    "steps": [
      200
    ],
    "timestamps": [
      "2026-03-18T21:33:44.419870"
    ],
    "values": [
      0.0
    ]
  },
  "target_mean": {
    "steps": [
      200
    ],
    "timestamps": [
      "2026-03-18T21:33:44.480665"
    ],
    "values": [
      0.17693761825561524
    ]
  },
  "td_error_abs": {
    "steps": [
      200
    ],
    "timestamps": [
      "2026-03-18T21:33:44.480660"
    ],
    "values": [
      0.06032839298248291
    ]
  },
  "test_ep_length_mean": {
    "steps": [
      200
    ],
    "timestamps": [
      "2026-03-18T21:33:44.898672"
    ],
    "values": [
      20.0
    ]
  },
  "test_return_mean": {
    "steps": [
      200
    ],
    "timestamps": [
      "2026-03-18T21:33:44.898603"
    ],
    "values": [
      0.005
    ]
  },
  "test_return_std": {
    "steps": [
      200
    ],
    "timestamps": [
      "2026-03-18T21:33:44.898665"
    ],
    "values": [
      0.049749371855330994
    ]
  }
}